epistemix_jupyterlab_theme/__init__.py
epistemix_jupyterlab_theme/_version.py
epistemix_jupyterlab_theme/labextension/package.json
epistemix_jupyterlab_theme/labextension/static/114.4491cf7d4dbeebc7c32a.js
epistemix_jupyterlab_theme/labextension/static/248.f9443ca2110b7c973b1d.js
epistemix_jupyterlab_theme/labextension/static/remoteEntry.5aa6bbe84b766a7292e2.js
epistemix_jupyterlab_theme/labextension/static/style.js
epistemix_jupyterlab_theme/labextension/static/third-party-licenses.json
epistemix_jupyterlab_theme/labextension/themes/epistemix_jupyterlab_theme/0f2b804d83aa13c6271b08f9f2520b618e26242ab367cc49496ae8f46098ca7b.ttf
epistemix_jupyterlab_theme/labextension/themes/epistemix_jupyterlab_theme/2950b5cd4ecb4b55bc596b0edaffc86351ce2383a3cdd7ce0b98e7f2fab701d7.ttf
epistemix_jupyterlab_theme/labextension/themes/epistemix_jupyterlab_theme/592b1aab4415f0d284a98595c2193ccc562f28d346ccd97b26533f139f0457c4.ttf
epistemix_jupyterlab_theme/labextension/themes/epistemix_jupyterlab_theme/880a5ca034333630ca5b815d123b9a413603d80034696781234cdca7c3edfb3e.ttf
epistemix_jupyterlab_theme/labextension/themes/epistemix_jupyterlab_theme/8d1f6724bc198e37bf19673c924d849e14d6849cd4dd87062965a9de2146c0f7.ttf
epistemix_jupyterlab_theme/labextension/themes/epistemix_jupyterlab_theme/8f1d4a50d50293b8baf69d8d5c9290918043d61fac6e57c80019c1a4af32639e.ttf
epistemix_jupyterlab_theme/labextension/themes/epistemix_jupyterlab_theme/a0e268dc1b1f0ffb4458eae85fbdaefb11b23cac9823cce48a6fb19350c49247.ttf
epistemix_jupyterlab_theme/labextension/themes/epistemix_jupyterlab_theme/e8f0be3066d690a90d616733fd1e5f79e9069f0416f9f3adf9a1e312942fda93.ttf
epistemix_jupyterlab_theme/labextension/themes/epistemix_jupyterlab_theme/ef36a50df9ad576cfa8a012e27dcc2f30d64cbc42cde5785ae9d27660acd4f3d.ttf
epistemix_jupyterlab_theme/labextension/themes/epistemix_jupyterlab_theme/index.css
epistemix_jupyterlab_theme/labextension/themes/epistemix_jupyterlab_theme/index.js
epistemix_jupyterlab_theme-0.3.6.dist-info/LICENSE
epistemix_jupyterlab_theme-0.3.6.dist-info/METADATA
epistemix_jupyterlab_theme-0.3.6.dist-info/WHEEL
epistemix_jupyterlab_theme-0.3.6.dist-info/top_level.txt
epistemix_jupyterlab_theme-0.3.6.dist-info/RECORD
